xai_easy/__init__.py
xai_easy/explain.py
xai_easy/utils.py
xai_easy/visualize.py
xai_easy-1.1.4.dist-info/licenses/LICENSE
xai_easy-1.1.4.dist-info/METADATA
xai_easy-1.1.4.dist-info/WHEEL
xai_easy-1.1.4.dist-info/top_level.txt
xai_easy-1.1.4.dist-info/RECORD
