Metadata-Version: 2.4
Name: xai-easy
Version: 1.1.4
Summary: A lightweight package for Explainable AI on ML models
Author-email: Prajwal Chopade <chopadeprajwal06@gmail.com>
License: MIT
Project-URL: Homepage, https://github.com/PrajwalChopade/xai_easy
Project-URL: Bug Tracker, https://github.com/PrajwalChopade/xai_easy/issues
License-File: LICENSE
Requires-Dist: scikit-learn
Requires-Dist: matplotlib
Requires-Dist: pandas
Requires-Dist: numpy
Dynamic: license-file
